[
    {
        "imgSrc": "./src/assets/bakumap.png",
        "isRecommended": true,
        "path": "/baku"
    },
    {
        "imgSrc": "./src/assets/lankaranmap.png",
        "isRecommended": false,
        "path": "/lankaran"
    },
    {
        "imgSrc": "./src/assets/shamakhimap.png",
        "isRecommended": true,
        "path": "/shamakhy"
    },
    {
        "imgSrc": "./src/assets/gubamap.png",
        "isRecommended": false,
        "path": "/guba"
    },
    {
        "imgSrc": "./src/assets/shakimap.png",
        "isRecommended": true,
        "path": "/shaki"
    },
    {
        "imgSrc": "./src/assets/ganjamap.png",
        "isRecommended": true,
        "path": "/ganja"
    },
    {
        "imgSrc": "./src/assets/gusarmap.png",
        "isRecommended": false,
        "path": "/gusar"
    },
    {
        "imgSrc": "./src/assets/ismaillymap.png",
        "isRecommended": true,
        "path": "/ismailly"
    },
    {
        "imgSrc": "./src/assets/khizimap.png",
        "isRecommended": false,
        "path": "/khizi"
    },
    {
        "imgSrc": "./src/assets/lerikmap.png",
        "isRecommended": true,
        "path": "/lerik"
    }
]